pyretries/__init__.py
pyretries/exceptions.py
pyretries/retry.py
pyretries/strategy.py
pyretries-0.2.10.dist-info/METADATA
pyretries-0.2.10.dist-info/WHEEL
pyretries-0.2.10.dist-info/RECORD
